drawbox/__init__.py
drawbox/cloudrain.py
DrawTool-1.0.0.dist-info/METADATA
DrawTool-1.0.0.dist-info/WHEEL
DrawTool-1.0.0.dist-info/top_level.txt
DrawTool-1.0.0.dist-info/RECORD
