Metadata-Version: 2.1
Name: DrawTool
Version: 1.0.0
Summary: A tool for creating raincloud plots
Home-page: https://github.com/JieLi-dd/DrawTool
Author: Jie Li
Author-email: 1508461021@qq.com
Classifier: Development Status :: 3 - Alpha
Classifier: Intended Audience :: Developers
Classifier: License :: OSI Approved :: MIT License
Classifier: Operating System :: OS Independent
Classifier: Programming Language :: Python :: 3
Classifier: Programming Language :: Python :: 3.7
Classifier: Programming Language :: Python :: 3.8
Classifier: Programming Language :: Python :: 3.9
Classifier: Programming Language :: Python :: 3.10
Classifier: Programming Language :: Python :: 3.11
Requires-Python: >=3.7
Requires-Dist: matplotlib (>=3.5.0)
Requires-Dist: numpy (>=1.20.0)
